[
  {
    "rank": 1,
    "title": "中国人在太空存粮多得超乎想象",
    "hot_value": " 1076563",
    "score": {
      "总体": 92,
      "新颖性": 19,
      "情感共鸣": 18,
      "传播潜力": 19,
      "娱乐价值": 18,
      "实用价值": 8,
      "市场潜力": 10,
      "总分": 92
    },
    "product_idea": {
      "产品名称": "太空粮仓",
      "核心功能": [
        "VR体验中国空间站的食物储备系统",
        "航天员菜单定制和营养搭配推荐",
        "太空食品科普教育和互动游戏",
        "模拟太空种植和食物培育",
        "航天食品文创产品和周边销售"
      ],
      "目标用户": {
        "用户画像": "航天爱好者、科普教育工作者、年轻家长及中小学生，对中国航天发展有强烈兴趣和自豪感",
        "痛点": "缺乏直观了解航天生活的渠道，航天科普内容枯燥难以吸引青少年",
        "行为特征": "乐于分享航天相关内容到社交媒体，愿意为航天周边产品付费，注重寓教于乐"
      },
      "价值主张": "通过沉浸式体验和互动学习，让普通民众深入了解中国航天的日常细节，将航天科技与生活趣味结合，打造独特的航天文化IP"
    }
  },
  {
    "rank": 2,
    "title": "英超日本国脚手持日军军官卡片合影",
    "hot_value": " 395634",
    "score": {
      "总体": 88,
      "新颖性": 16,
      "情感共鸣": 19,
      "传播潜力": 18,
      "娱乐价值": 17,
      "实用价值": 9,
      "市场潜力": 9,
      "总分": 88
    },
    "product_idea": {
      "产品名称": "历史镜鉴",
      "核心功能": [
        "历史影像识别和敏感内容AI筛查",
        "运动员文化敏感性培训和提醒",
        "历史知识科普和背景解读",
        "跨国文化交流行为准则数据库",
        "舆情风险预警和应对建议"
      ],
      "目标用户": {
        "用户画像": "体育俱乐部管理层、国际运动员、跨国企业员工、文化敏感性培训师",
        "痛点": "缺乏对历史敏感细节的认知，容易在跨文化交流中触碰雷区，引发公关危机",
        "行为特征": "需要快速了解不同国家的文化禁忌，重视个人品牌形象和职业发展"
      },
      "价值主张": "通过AI技术识别历史敏感内容，为国际人士提供文化敏感性指导，防范无意中的历史冒犯行为，维护个人和机构形象"
    }
  },
  {
    "rank": 3,
    "title": "黄土高原变绿了",
    "hot_value": " 355570",
    "score": {
      "总体": 91,
      "新颖性": 18,
      "情感共鸣": 19,
      "传播潜力": 18,
      "娱乐价值": 18,
      "实用价值": 9,
      "市场潜力": 9,
      "总分": 91
    },
    "product_idea": {
      "产品名称": "生态眼",
      "核心功能": [
        "生态变化卫星影像对比和历史追溯",
        "个人碳足迹追踪和减排建议",
        "生态建设项目参与和捐助平台",
        "绿色成就社交媒体分享和互动",
        "生态文化旅游路线规划和导览"
      ],
      "目标用户": {
        "用户画像": "环保志愿者、生态摄影师、旅行爱好者、环保意识强烈的年轻人和家庭",
        "痛点": "对生态环境改善效果缺乏直观感知，想参与环保但不知如何行动",
        "行为特征": "关注可持续发展，喜欢在社交媒体分享环保内容，愿意为环保项目花钱"
      },
      "价值主张": "通过卫星影像和AI分析展示中国生态修复成就，让用户直观看到环境改善效果，提供参与生态保护的具体行动路径"
    }
  },
  {
    "rank": 4,
    "title": "电影马腾你别走定档",
    "hot_value": " 351862",
    "score": {
      "总体": 74,
      "新颖性": 13,
      "情感共鸣": 18,
      "传播潜力": 17,
      "娱乐价值": 18,
      "实用价值": 4,
      "市场潜力": 4,
      "总分": 74
    },
    "product_idea": {
      "产品名称": "影伴",
      "核心功能": [
        "电影档期倒计时和预售提醒",
        "观影计划管理和朋友邀约",
        "电影台词金句收藏和分享",
        "观影后感社区和评分系统",
        "主演影视作品全览和追踪"
      ],
      "目标用户": {
        "用户画像": "电影爱好者、年轻情侣、朋友群体、追剧追星的粉丝群体",
        "痛点": "错过喜欢的电影档期，观影体验缺乏社交互动，观影后感想无处分享",
        "行为特征": "定期观影，喜欢和朋友一起看电影，愿意为优质电影付费，热衷于影视讨论"
      },
      "价值主张": "打造电影观影全流程陪伴工具，从期待到观影再到分享，增强观影社交体验，让用户不错过任何想看的电影"
    }
  },
  {
    "rank": 5,
    "title": "Uzi 复出",
    "hot_value": " 346706",
    "score": {
      "总体": 85,
      "新颖性": 14,
      "情感共鸣": 20,
      "传播潜力": 20,
      "娱乐价值": 17,
      "实用价值": 7,
      "市场潜力": 7,
      "总分": 85
    },
    "product_idea": {
      "产品名称": "电竞传奇",
      "核心功能": [
        "电竞选手复出追踪和表现分析",
        "玩家能力退化评估和训练方案",
        "黄金年龄段电竞选手生涯规划",
        "电竞赛事历史数据和辉煌时刻重温",
        "复出选手心理辅导和压力管理"
      ],
      "目标用户": {
        "用户画像": "电竞职业选手、退役选手、电竞爱好者、电竞俱乐部管理层",
        "痛点": "电竞选手职业生涯短暂，缺乏科学的退役后复训体系，复出表现难以预测",
        "行为特征": "对电竞有深厚感情，关注明星选手动态，愿意为提升技术付费学习"
      },
      "价值主张": "通过科学的训练方法和数据分析，帮助电竞选手延长职业生涯，为有复出意愿的选手提供系统化的评估和训练方案，延续电竞梦想"
    }
  },
  {
    "rank": 6,
    "title": "长安二十四计",
    "hot_value": "剧集 337637",
    "score": {
      "总体": 78,
      "新颖性": 17,
      "情感共鸣": 16,
      "传播潜力": 17,
      "娱乐价值": 18,
      "实用价值": 5,
      "市场潜力": 5,
      "总分": 78
    },
    "product_idea": {
      "产品名称": "智谋录",
      "核心功能": [
        "古装剧中的历史策略解析",
        "职场和生活场景的策略应用指南",
        "历史人物谋略学习课程",
        "策略游戏和剧本杀创意生成",
        "古装剧集穿帮错误考证和讨论"
      ],
      "目标用户": {
        "用户画像": "历史爱好者、古装剧粉丝、职场新人、编剧和游戏设计师",
        "痛点": "枯燥的历史策略难以应用到现代生活，缺乏有趣的策略学习工具",
        "行为特征": "喜欢思考分析，关注古装剧中的人物关系，将看剧作为学习和娱乐方式"
      },
      "价值主张": "从热门古装剧中提取历史智慧和谋略，通过现代场景应用案例，让策略学习变得有趣实用，将娱乐转化为知识"
    }
  },
  {
    "rank": 7,
    "title": "沈腾的征信都扫不了共享单车",
    "hot_value": " 272256",
    "score": {
      "总体": 86,
      "新颖性": 17,
      "情感共鸣": 18,
      "传播潜力": 20,
      "娱乐价值": 17,
      "实用价值": 8,
      "市场潜力": 6,
      "总分": 86
    },
    "product_idea": {
      "产品名称": "信用守护者",
      "核心功能": [
        "个人信息泄露风险扫描和预警",
        "征信报告智能解读和相关性分析",
        "日常行为对信用影响模拟器",
        "明星及名人征信健康度科普",
        "信用修复指导和法律咨询服务"
      ],
      "目标用户": {
        "用户画像": "年轻上班族、刚步入社会的毕业生、自由职业者、征信问题困扰者",
        "痛点": "对征信体系认知不足，担心无意间影响信用评分，缺乏降低信用风险的工具",
        "行为特征": "使用共享经济和信贷产品频繁，关注名人生活细节，重视个人信用记录"
      },
      "价值主张": "通过明星案例和趣味测评，普及征信知识，让复杂的信用体系变得易懂易用，帮助用户建立健康的信用习惯"
    }
  },
  {
    "rank": 8,
    "title": "手机壳爱马仕一年狂卖36亿",
    "hot_value": " 224996",
    "score": {
      "总体": 89,
      "新颖性": 19,
      "情感共鸣": 17,
      "传播潜力": 19,
      "娱乐价值": 17,
      "实用价值": 8,
      "市场潜力": 9,
      "总分": 89
    },
    "product_idea": {
      "产品名称": "壳艺空间",
      "核心功能": [
        "潮流手机壳设计和个性化定制",
        "奢侈品级别材质和工艺选择",
        "明星同款手机壳复刻和推荐",
        "限量版手机壳收藏和交易平台",
        "手机壳设计师社区和孵化计划"
      ],
      "目标用户": {
        "用户画像": "手机壳收藏家、潮流达人、奢侈品爱好者、年轻消费群体",
        "痛点": "难以找到独特且高品质的手机壳，奢侈品手机壳价格不透明，缺乏收藏价值",
        "行为特征": "频繁更换手机壳表达个性，愿意为设计感付费，关注潮流趋势和明星搭配"
      },
      "价值主张": "打造手机壳界的"爱马仕"，提供高品质、设计独特、具有收藏价值的手机壳，让手机壳成为时尚配饰和文化符号"
    }
  },
  {
    "rank": 9,
    "title": "国考的难度到底有多大",
    "hot_value": " 224510",
    "score": {
      "总体": 82,
      "新颖性": 12,
      "情感共鸣": 20,
      "传播潜力": 18,
      "娱乐价值": 15,
      "实用价值": 9,
      "市场潜力": 8,
      "总分": 82
    },
    "product_idea": {
      "产品名称": "公考军师",
      "核心功能": [
        "AI模拟行测和申论评分系统",
        "历年考点大数据分析和趋势预测",
        "个人薄弱环节专项训练计划",
        "考生心理压力和焦虑管理",
        "考后复盘和下一年的规划建议"
      ],
      "目标用户": {
        "用户画像": "应届毕业生、在职备考人员、多次失败的考生、体制内转正人员",
        "痛点": "不知考试难度有多深，备考效率低下，缺乏科学的备考方法",
        "行为特征": "投入大量时间和金钱备考，对考试信息极度渴望，愿意试错寻找最佳路径"
      },
      "价值主张": "提供真实的考试难度量化评估，结合AI技术分析个人强弱项，提供科学备考路径，让公考从"盲目备考"变为"精准打击""
    }
  },
  {
    "rank": 10,
    "title": "美乌4小时会谈细节曝光",
    "hot_value": " 223362",
    "score": {
      "总体": 72,
      "新颖性": 14,
      "情感共鸣": 14,
      "传播潜力": 16,
      "娱乐价值": 14,
      "实用价值": 7,
      "市场潜力": 7,
      "总分": 72
    },
    "product_idea": {
      "产品名称": "外交辞典",
      "核心功能": [
        "外交谈判场景AI模拟训练",
        "国际关系术语和暗语解读",
        "重大外交事件时间轴梳理",
        "外交肢体语言和心理分析",
        "外交谈判话术和策略学习"
      ],
      "目标用户": {
        "用户画像": "国际关系专业学生、外交官、跨国公司国际业务人员、外交爱好者",
        "痛点": "外交新闻看不懂深层含义，缺乏对外交技巧的了解，不知道如何分析国际事件",
        "行为特征": "关注国际时政新闻，喜欢分析大国博弈，渴望了解外交幕后故事"
      },
      "价值主张": "将复杂的外交会谈转化为易懂可学的案例分析，让普通民众和国际关系从业者快速掌握外交读心术，提升国际视野"
    }
  },
  {
    "rank": 11,
    "title": "朱珠 面无表情把老公挤开",
    "hot_value": " 222505",
    "score": {
      "总体": 73,
      "新颖性": 15,
      "情感共鸣": 16,
      "传播潜力": 18,
      "娱乐价值": 16,
      "实用价值": 4,
      "市场潜力": 4,
      "总分": 73
    },
    "product_idea": {
      "产品名称": "夫妻微表情",
      "核心功能": [
        "明星夫妻互动微表情AI分析",
        "日常夫妻关系行为模式识别",
        "情侣间无意识行为的趣味解读",
        "明星婚姻相处之道案例库",
        "情感互动模仿和学习社区"
      ],
      "目标用户": {
        "用户画像": "年轻夫妻、恋爱中情侣、明星八卦爱好者、情感咨询师",
        "痛点": "不懂解读伴侣的无意识行为，对明星婚姻生活好奇但缺乏深度分析",
        "行为特征": "热衷于观察明星互动细节，模仿喜欢的情侣行为模式，寻求情感关系指导"
      },
      "价值主张": "通过微表情和行为心理学分析明星夫妻的互动细节，让普通用户学习处理亲密关系的技巧，将娱乐八卦转化为情感智慧"
    }
  },
  {
    "rank": 12,
    "title": "一身聚酯纤维的我怎么敢碰纯毛的你",
    "hot_value": " 220312",
    "score": {
      "总体": 83,
      "新颖性": 17,
      "情感共鸣": 19,
      "传播潜力": 18,
      "娱乐价值": 17,
      "实用价值": 6,
      "市场潜力": 6,
      "总分": 83
    },
    "product_idea": {
      "产品名称": "穿搭社会学",
      "核心功能": [
        "服装材质和价格反向搜索引擎",
        "基于衣品的社交场景推荐",
        "衣服品牌和价格区间识别",
        "穿搭身份暗示和社交信号分析",
        "不同场合的穿搭段位测试"
      ],
      "目标用户": {
        "用户画像": "职场新人、社交焦虑者、时尚爱好者、身份认同探索者",
        "痛点": "担心穿搭不当在社交场合失礼，不懂衣服品牌蕴含的社交信号",
        "行为特征": "出门前反复检查穿着，关注别人衣物品牌，希望通过穿搭获得认同"
      },
      "价值主张": "聚焦穿搭背后的社会学意义，帮助用户在社交场合做出得体的穿搭选择，用科技消除因服装材质、品牌带来的社交焦虑"
    }
  },
  {
    "rank": 13,
    "title": "日本发布高市早苗外交场面引群嘲",
    "hot_value": " 218988",
    "score": {
      "总体": 75,
      "新颖性": 13,
      "情感共鸣": 15,
      "传播潜力": 18,
      "娱乐价值": 15,
      "实用价值": 7,
      "市场潜力": 7,
      "总分": 75
    },
    "product_idea": {
      "产品名称": "外交脱口秀",
      "核心功能": [
        "国际政治人物失言和出糗合集",
        "外交官表现评分和排名系统",
        "外交场合应对失误的搞笑解读",
        "外交辞令vs真实意图漫画式翻译",
        "用户投票最尴尬外交瞬间榜单"
      ],
      "目标用户": {
        "用户画像": "时事热点关注者、脱口秀爱好者、政治讽刺文化消费者、年轻一代国际观察者",
        "痛点": "严肃的国际新闻难以理解，缺乏轻松了解国际政治的入口",
        "行为特征": "喜欢通过段子和梗图了解新闻，热衷讨论政治人物失误，追求政治表达的新颖方式"
      },
      "价值主张": "用段子和幽默的方式解读国际政治失误，让严肃的外交场合变得有趣易懂，降低了解国际政治的门槛"
    }
  },
  {
    "rank": 14,
    "title": "现在就出发 后期",
    "hot_value": "综艺 217889",
    "score": {
      "总体": 68,
      "新颖性": 12,
      "情感共鸣": 14,
      "传播潜力": 16,
      "娱乐价值": 16,
      "实用价值": 5,
      "市场潜力": 5,
      "总分": 68
    },
    "product_idea": {
      "产品名称": "综艺精剪师",
      "核心功能": [
        "旅行综艺视频素材自动精剪",
        "旅行Vlog一键后期和滤镜推荐",
        "综艺节目剪辑套路和技巧分析",
        "旅行精彩片段音乐匹配",
        "综艺节目后期制作技能培训"
      ],
      "目标用户": {
        "用户画像": "旅行博主Vloger、短视频创作者、综艺节目粉丝、旅行爱好者",
        "痛点": "旅行视频素材难以剪辑，找不到合适的剪辑风格，缺乏后期制作技巧",
        "行为特征": "拍摄大量旅行素材但不知如何剪辑，模仿喜欢的综艺节目风格，希望提升视频制作水平"
      },
      "价值主张": "借鉴顶级综艺节目的后期制作手法，帮用户快速提升Vlog制作水平，让每个人的旅行视频都像综艺一样精彩"
    }
  },
  {
    "rank": 15,
    "title": "司机鸣笛无效轧到睡狗",
    "hot_value": " 216548",
    "score": {
      "总体": 71,
      "新颖性": 15,
      "情感共鸣": 14,
      "传播潜力": 17,
      "娱乐价值": 16,
      "实用价值": 5,
      "市场潜力": 4,
      "总分": 71
    },
    "product_idea": {
      "产品名称": "萌宠护卫",
      "核心功能": [
        "宠物在交通环境危险预警系统",
        "流浪动物识别和救助平台",
        "驾驶员动物避让培训游戏",
        "宠物主人安全溜宠工具推荐",
        "路遇动物后的应急处理指导"
      ],
      "目标用户": {
        "用户画像": "宠物主人、司机、动物保护组织志愿者、城市交通规划人员",
        "痛点": "无法预料宠物在马路的危险行为，缺乏动物避让的应对知识",
        "行为特征": "担心宠物安全，愿意为保护动物付费，关注动物相关热点事件"
      },
      "价值主张": "让司机在危险发生前识别动物行为风险，通过科技手段减少交通中的动物伤亡，促进人车动物和谐共处"
    }
  },
  {
    "rank": 16,
    "title": "谁在买200元一粒的流感药",
    "hot_value": " 215571",
    "score": {
      "总体": 85,
      "新颖性": 16,
      "情感共鸣": 19,
      "传播潜力": 17,
      "娱乐价值": 14,
      "实用价值": 9,
      "市场潜力": 10,
      "总分": 85
    },
    "product_idea": {
      "产品名称": "药价侦探",
      "核心功能": [
        "药品价格差异大数据分析",
        "流感药物替代选择智能推荐",
        "药品价格趋势预测",
        "特殊药品购买人群画像分析",
        "药企定价策略透明度报告"
      ],
      "目标用户": {
        "用户画像": "慢性病患者、老年人家属、医药代表、公共卫生研究员、政府价格监管人员",
        "痛点": "药品价格不透明，不知高价药是否真的必要，缺乏专业药品咨询",
        "行为特征": "对高价药感到困惑，比较不同药品价格，在药品支出上有预算压力"
      },
      "价值主张": "通过药品价格和效果数据分析，让消费者明白为何存在高价药，提供基于价值的选择建议，推动药品价格合理化"
    }
  },
  {
    "rank": 17,
    "title": "25岁小伙离世前称加班累到嘴巴渗血",
    "hot_value": " 214070",
    "score": {
      "总体": 92,
      "新颖性": 18,
      "情感共鸣": 20,
      "传播潜力": 19,
      "娱乐价值": 12,
      "实用价值": 12,
      "市场潜力": 11,
      "总分": 92
    },
    "product_idea": {
      "产品名称": "工作健康守护",
      "核心功能": [
        "加班健康风险AI评估和预警",
        "身体发出危险信号的识别指南",
        "压力导致的身体症状跟踪日志",
        "法律保护下拒绝过度加班的话术",
        "猝死前身体预警症状科普"
      ],
      "目标用户": {
        "用户画像": "互联网从业者、医护人员、年轻人白领、HR和工会人员",
        "痛点": "长期加班但忽视健康风险，不清楚身体发出的危险信号，不知道如何维权",
        "行为特征": "工作压力大但缺乏健康管理，对劳动法了解不足，关注过劳死相关新闻"
      },
      "价值主张": "通过真实案例和科学数据警示加班危害，帮助职场人识别健康风险信号，提供合法维权的工具和知识，挽救生命"
    }
  },
  {
    "rank": 18,
    "title": "幼师等招聘可依法查询吸毒记录",
    "hot_value": " 213820",
    "score": {
      "总体": 77,
      "新颖性": 14,
      "情感共鸣": 15,
      "传播潜力": 16,
      "娱乐价值": 13,
      "实用价值": 10,
      "市场潜力": 9,
      "总分": 77
    },
    "product_idea": {
      "产品名称": "资质守护",
      "核心功能": [
        "特定行业从业资格自动核查系统",
        "背景调查全程记录和存证",
        "各行业就业准入条件数据库",
        "求职者和用人单位双向查询平台",
        "违法行为历史对职业影响评估"
      ],
      "目标用户": {
        "用户画像": "幼儿园和学校管理人员、招聘负责人、人力资源从业者、求职者",
        "痛点": "无法有效识别有不良记录的从业人员，缺乏合法的背景查询渠道",
        "行为特征": "对儿童安全高度负责，细致审查员工资质，关注法律和政策的更新"
      },
      "价值主张": "为敏感行业提供合法合规的背景调查工具，确保儿童、患者等特殊人群的安全，让招聘更放心、更规范"
    }
  },
  {
    "rank": 19,
    "title": "故意传播艾滋病涉嫌违法犯罪",
    "hot_value": " 206214",
    "score": {
      "总体": 84,
      "新颖性": 16,
      "情感共鸣": 17,
      "传播潜力": 17,
      "娱乐价值": 12,
      "实用价值": 11,
      "市场潜力": 11,
      "总分": 84
    },
    "product_idea": {
      "产品名称": "健康边界",
      "核心功能": [
        "传染病法律知识科普和查询",
        "伴侣健康状况知情权保护",
        "隐私保护和疾病报告的平衡点指导",
        "受害者法律援助和取证指导",
        "高危行为和违法风险预警"
      ],
      "目标用户": {
        "用户画像": "性教育工作者、疾控中心宣传员、法律工作者、关注健康防护的年轻人",
        "痛点": "不了解故意传播疾病的法律后果，缺乏防范意识，不懂得如何维权",
        "行为特征": "关注健康类社会新闻，重视自我保护，对社会危害性信息敏感"
      },
      "价值主张": "用真实案例普及传染病相关法律法规，提高公众防范意识，明确法律边界，保护受害者合法权益"
    }
  },
  {
    "rank": 20,
    "title": "高市早苗的言论侵犯了中国的主权",
    "hot_value": " 200308",
    "score": {
      "总体": 69,
      "新颖性": 11,
      "情感共鸣": 16,
      "传播潜力": 15,
      "娱乐价值": 12,
      "实用价值": 8,
      "市场潜力": 7,
      "总分": 69
    },
    "product_idea": {
      "产品名称": "主权之声",
      "核心功能": [
        "国际争议言论实时监控和预警",
        "中国主权问题知识库和快速回应",
        "民众爱国情感表达和理性讨论平台",
        "外交部门发言人经典回应案例",
        "领土和主权争议的图文科普"
      ],
      "目标用户": {
        "用户画像": "爱国青年、国际关系关注者、海外华人、历史教育工作者",
        "痛点": "不了解历史背景无法理性反驳，情绪激动但缺乏事实依据，想维护主权但方式不当",
        "行为特征": "关注涉华国际言论，对领土主权问题高度敏感，乐于转发爱国内容"
      },
      "价值主张": "提供基于历史事实和法律依据的主权问题回应工具，让爱国表达更加有理有据，理性维护国家利益和民族尊严"
    }
  }
]
