[
  {
    "rank": 1,
    "title": "就说看时装周真能学到东西",
    "scores": {
      "novelty": 18,
      "resonance": 16,
      "viral": 18,
      "entertainment": 17,
      "practical": 6,
      "market": 8
    },
    "total_score": 83,
    "grade": "优秀",
    "product_idea": {
      "name": "AI穿搭魔镜：时装周同款生成器",
      "features": "用户上传日常照片，AI识别身形并实时将其替换为时装周T台同款造型，提供平替单品购买链接及穿搭教学。",
      "target_users": "时尚爱好者、穿搭小白、短视频用户。",
      "value_proposition": "打破时尚壁垒，让普通人也能通过趣味方式体验并掌握高级时尚技巧。"
    }
  },
  {
    "rank": 2,
    "title": "万万没想到干噎汤圆又来了",
    "scores": {
      "novelty": 16,
      "resonance": 14,
      "viral": 17,
      "entertainment": 16,
      "practical": 4,
      "market": 7
    },
    "total_score": 74,
    "grade": "良好",
    "product_idea": {
      "name": "“饱腹感”特训：奇葩零食盲盒",
      "features": "每月订阅包含各种高难度、奇葩口感的网红零食（如干噎汤圆），附带挑战任务卡和Vlog拍摄教程。",
      "target_users": "猎奇向年轻消费者、美食博主、大学生。",
      "value_proposition": "提供超乎预期的味蕾刺激和社交谈资，将食物消费转化为娱乐体验。"
    }
  },
  {
    "rank": 3,
    "title": "这份粮食成绩单请查收",
    "scores": {
      "novelty": 5,
      "resonance": 8,
      "viral": 6,
      "entertainment": 3,
      "practical": 5,
      "market": 4
    },
    "total_score": 31,
    "grade": "普通",
    "product_idea": {
      "name": "农业溯源可视化平台",
      "features": "扫描农产品二维码，通过VR或互动图表展示该粮食从种植到收获的全过程及产量数据。",
      "target_users": "关注食品安全的家庭、教育机构。",
      "value_proposition": "通过透明的数据可视化增强消费者对国产粮食的信任感和安全感。"
    }
  },
  {
    "rank": 4,
    "title": "土耳其空军一架F16战机坠毁",
    "scores": {
      "novelty": 10,
      "resonance": 8,
      "viral": 9,
      "entertainment": 2,
      "practical": 2,
      "market": 2
    },
    "total_score": 33,
    "grade": "普通",
    "product_idea": {
      "name": "全球防务要闻日报",
      "features": "聚合全球突发军事新闻并提供即时推送到手机，附带装备参数解析和3D模型演示。",
      "target_users": "军迷、防务分析师、相关行业从业者。",
      "value_proposition": "为硬核军事爱好者提供专业、及时且深度可视化的资讯服务。"
    }
  },
  {
    "rank": 5,
    "title": "外交部回应英法或供乌核武器",
    "scores": {
      "novelty": 12,
      "resonance": 15,
      "viral": 14,
      "entertainment": 2,
      "practical": 2,
      "market": 2
    },
    "total_score": 47,
    "grade": "普通",
    "product_idea": {
      "name": "地缘政治风险评估看板",
      "features": "针对国际热点新闻（如核武器动态）分析对全球资产、供应链的影响指数，提供避险建议。",
      "target_users": "投资者、外贸从业者、财经分析师。",
      "value_proposition": "将宏大的国际政治新闻转化为具体的个人资产保护参考数据。"
    }
  },
  {
    "rank": 6,
    "title": "伊朗大规模军演 试射多种导弹",
    "scores": {
      "novelty": 11,
      "resonance": 12,
      "viral": 12,
      "entertainment": 3,
      "practical": 2,
      "market": 2
    },
    "total_score": 42,
    "grade": "普通",
    "product_idea": {
      "name": "装备科技百科",
      "features": "拆解新闻中亮相的新型武器装备，用3D互动模型展示其内部机械结构和科技原理。",
      "target_users": "工科学生、军迷、科技爱好者。",
      "value_proposition": "硬核科普，满足公众对尖端军事技术的探索欲。"
    }
  },
  {
    "rank": 7,
    "title": "海警在金门附近海域常态执法巡查",
    "scores": {
      "novelty": 14,
      "resonance": 16,
      "viral": 15,
      "entertainment": 4,
      "practical": 2,
      "market": 2
    },
    "total_score": 53,
    "grade": "普通",
    "product_idea": {
      "name": "海域态势感知小程序",
      "features": "基于公开数据的海上地图应用，实时更新重点海域执法动态与历史航线对比。",
      "target_users": "时政关注者、涉海业务从业者。",
      "value_proposition": "提供直观的海洋主权动态信息，增强国民海洋意识。"
    }
  },
  {
    "rank": 8,
    "title": "媒体评默茨访华",
    "scores": {
      "novelty": 8,
      "resonance": 9,
      "viral": 8,
      "entertainment": 2,
      "practical": 2,
      "market": 2
    },
    "total_score": 31,
    "grade": "普通",
    "product_idea": {
      "name": "外交辞令翻译器",
      "features": "输入外交官或媒体发言，输出通俗直白的“大白话”解读及背后的利益关系分析。",
      "target_users": "新闻读者、职场新人、留学生。",
      "value_proposition": "降低政治阅读门槛，帮助用户快速看懂国际局势背后的门道。"
    }
  },
  {
    "rank": 9,
    "title": "朱雀三号计划再次挑战回收",
    "scores": {
      "novelty": 16,
      "resonance": 15,
      "viral": 16,
      "entertainment": 14,
      "practical": 6,
      "market": 8
    },
    "total_score": 75,
    "grade": "良好",
    "product_idea": {
      "name": "航天任务模拟经营手游",
      "features": "玩家扮演航天公司CEO，从研发火箭（如朱雀三号）到发射回收全流程模拟，体验真实物理引擎。",
      "target_users": "游戏玩家、科技迷、青少年。",
      "value_proposition": "让用户体验硬核航天科技的魅力，科普航天知识同时满足经营成就感。"
    }
  },
  {
    "rank": 10,
    "title": "阿富汗与巴基斯坦在边境爆发冲突",
    "scores": {
      "novelty": 9,
      "resonance": 10,
      "viral": 10,
      "entertainment": 2,
      "practical": 2,
      "market": 2
    },
    "total_score": 35,
    "grade": "普通",
    "product_idea": {
      "name": "全球安全出行助手",
      "features": "针对出境游或务工人员，根据地区冲突实时更新安全预警地图，规划避险路线。",
      "target_users": "出境商旅人士、外派员工。",
      "value_proposition": "为特殊地区出行者提供关键的生命安全保障信息。"
    }
  },
  {
    "rank": 11,
    "title": "张家鸣加盟伯恩利",
    "scores": {
      "novelty": 10,
      "resonance": 12,
      "viral": 12,
      "entertainment": 8,
      "practical": 3,
      "market": 5
    },
    "total_score": 50,
    "grade": "普通",
    "product_idea": {
      "name": "球星卡数字化交易与对战平台",
      "features": "结合球星转会现实数据，发行数字球星卡，拥有者可组建队伍在线进行模拟对战。",
      "target_users": "足球迷、卡牌收藏者。",
      "value_proposition": "将体育 fandom 与数字化 collectibles 结合，增加球迷互动乐趣。"
    }
  },
  {
    "rank": 12,
    "title": "网传医院有安乐死胶囊系谣言",
    "scores": {
      "novelty": 12,
      "resonance": 10,
      "viral": 10,
      "entertainment": 2,
      "practical": 7,
      "market": 4
    },
    "total_score": 45,
    "grade": "普通",
    "product_idea": {
      "name": "AI医疗谣言粉碎机",
      "features": "用户输入听到的医疗传闻（如安乐死胶囊），AI快速检索权威信源进行辟谣并生成科普报告。",
      "target_users": "中老年群体、关注健康的普通大众。",
      "value_proposition": "打击医疗伪科学，提供权威可信的健康信息检索入口。"
    }
  },
  {
    "rank": 13,
    "title": "WBG战胜IG",
    "scores": {
      "novelty": 12,
      "resonance": 16,
      "viral": 16,
      "entertainment": 14,
      "practical": 4,
      "market": 7
    },
    "total_score": 69,
    "grade": "良好",
    "product_idea": {
      "name": "电竞高光时刻一键剪辑App",
      "features": "自动识别电竞比赛录像中的精彩团战或击杀画面，一键生成带特效的短视频并同步分发。",
      "target_users": "电竞观众、游戏博主、解说。",
      "价值_proposition": "降低电竞内容创作门槛，让粉丝秒变内容创作者。"
    }
  },
  {
    "rank": 14,
    "title": "全球首创全涵道式eVTOL试飞",
    "scores": {
      "novelty": 18,
      "resonance": 14,
      "viral": 16,
      "entertainment": 15,
      "practical": 7,
      "market": 8
    },
    "total_score": 78,
    "grade": "良好",
    "product_idea": {
      "name": "未来出行：城市空中打车模拟器",
      "features": "利用VR体验全涵道式eVTOL的飞行视角，并模拟未来城市低空出行的场景。",
      "target_users": "科技尝鲜者、科幻迷、潜在乘客。",
      "value_proposition": "提前体验未来的低空经济生活方式，普及新型交通工具认知。"
    }
  },
  {
    "rank": 15,
    "title": "詹姆斯错失绝杀",
    "scores": {
      "novelty": 12,
      "resonance": 16,
      "viral": 17,
      "entertainment": 14,
      "practical": 3,
      "market": 5
    },
    "total_score": 67,
    "grade": "良好",
    "product_idea": {
      "name": "球星打气/吐槽表情包生成器",
      "features": "基于比赛热点瞬间（如错失绝杀），自动生成带有幽默文案的动图或表情包。",
      "target_users": "篮球迷、社交媒体用户。",
      "价值_proposition": "将竞技体育的戏剧性瞬间转化为社交货币，放大情绪价值。"
    }
  },
  {
    "rank": 16,
    "title": "骑士109:94大胜尼克斯",
    "scores": {
      "novelty": 10,
      "resonance": 12,
      "viral": 13,
      "entertainment": 12,
      "practical": 3,
      "market": 4
    },
    "total_score": 54,
    "grade": "普通",
    "product_idea": {
      "name": "赛后数据透视镜",
      "features": "AR扫描比赛集锦画面，实时显示球员热区图和胜负贡献值等深度数据。",
      "target_users": "战术爱好者、资深球迷。",
      "value_proposition": "超越传统解说，提供数据驱动的观赛视角，理解比赛胜负手。"
    }
  },
  {
    "rank": 17,
    "title": "电视剧告白官宣",
    "scores": {
      "novelty": 11,
      "resonance": 14,
      "viral": 14,
      "entertainment": 12,
      "practical": 4,
      "market": 7
    },
    "total_score": 62,
    "grade": "良好",
    "product_idea": {
      "name": "剧情预测社交平台",
      "features": "用户基于预告片对剧情走向进行押注或预测，剧集更新后揭晓结果并排名。",
      "target_users": "剧粉、悬疑爱好者。",
      "价值_proposition": "增强追剧过程中的互动性和参与感，变被动观看为主动预测。"
    }
  },
  {
    "rank": 18,
    "title": "特朗普：我们赢得太多了",
    "scores": {
      "novelty": 13,
      "resonance": 15,
      "viral": 16,
      "entertainment": 13,
      "practical": 2,
      "market": 3
    },
    "total_score": 62,
    "grade": "良好",
    "product_idea": {
      "name": "政客语录梗图生成器",
      "features": "结合时政热点人物的金句，一键生成不同风格的讽刺或支持类梗图。",
      "target_users": "时政关注者、网民。",
      "价值_proposition": "以幽默解构严肃政治，满足用户的表达欲和创作欲。"
    }
  },
  {
    "rank": 19,
    "title": "电影镖人累计票房破9亿",
    "scores": {
      "novelty": 14,
      "resonance": 14,
      "viral": 14,
      "entertainment": 16,
      "practical": 5,
      "market": 8
    },
    "total_score": 71,
    "grade": "良好",
    "product_idea": {
      "name": "漫改电影宇宙通行证",
      "features": "打通同一IP（如镖人）的漫画与电影，观影可解锁漫画隐藏彩蛋，购买周边可兑换电影积分。",
      "target_users": "原著粉、电影观众。",
      "价值_proposition": "深度挖掘IP价值，为影视作品建立长效的粉丝经济生态。"
    }
  },
  {
    "rank": 20,
    "title": "飞驰3终于迎来光辉岁月大合唱",
    "scores": {
      "novelty": 13,
      "resonance": 17,
      "viral": 16,
      "entertainment": 16,
      "practical": 4,
      "market": 7
    },
    "total_score": 73,
    "grade": "良好",
    "product_idea": {
      "name": "影院K歌模式",
      "features": "针对音乐电影场次，开发App同步影院原声，让观众在特定环节可以用手机麦克风参与全场合唱。",
      "target_users": "电影观众、音乐爱好者。",
      "价值_proposition": "复活影院仪式感，将观影体验升级为集体参与的演唱会体验。"
    }
  }
]