{
  "fetch_time": "2026-02-10T22:30:03.054170",
  "source": "weibo",
  "api_code": 200,
  "api_message": "success",
  "topics": [
    {
      "rank": 1,
      "title": "男子为避酒店春节涨价花1万多租房",
      "hot_value": " 314768",
      "url": "",
      "description": ""
    },
    {
      "rank": 2,
      "title": "付费假装上班被要求不迟到不玩手机",
      "hot_value": " 220805",
      "url": "",
      "description": ""
    },
    {
      "rank": 3,
      "title": "中国无人机大山里运腊肠",
      "hot_value": " 177914",
      "url": "",
      "description": ""
    },
    {
      "rank": 4,
      "title": "天猫年货节最后冲刺24小时",
      "hot_value": " ",
      "url": "",
      "description": ""
    },
    {
      "rank": 5,
      "title": "中国跳台滑雪再创历史",
      "hot_value": " 60239",
      "url": "",
      "description": ""
    },
    {
      "rank": 6,
      "title": "海外已夸爆Seedance2.0",
      "hot_value": " 50063",
      "url": "",
      "description": "火热"
    },
    {
      "rank": 7,
      "title": "短道队多人为孙龙发声",
      "hot_value": " 44806",
      "url": "",
      "description": ""
    },
    {
      "rank": 8,
      "title": "韩媒质问这还是体育吗",
      "hot_value": " 44231",
      "url": "",
      "description": ""
    },
    {
      "rank": 9,
      "title": "金博洋短节目86.55分",
      "hot_value": " 40672",
      "url": "",
      "description": ""
    },
    {
      "rank": 10,
      "title": "德云社封箱",
      "hot_value": "演出 34927",
      "url": "",
      "description": ""
    },
    {
      "rank": 11,
      "title": "成毅两京十五日杀青",
      "hot_value": " 29770",
      "url": "",
      "description": ""
    },
    {
      "rank": 12,
      "title": "肖战",
      "hot_value": " 29638",
      "url": "",
      "description": ""
    },
    {
      "rank": 13,
      "title": "李谷一回应缺席马年春晚",
      "hot_value": " 29194",
      "url": "",
      "description": ""
    },
    {
      "rank": 14,
      "title": "射雕英雄传侠之大者金像奖0提",
      "hot_value": "盛典 28625",
      "url": "",
      "description": ""
    },
    {
      "rank": 15,
      "title": "74岁肥猫被医生建议注射药物镇痛",
      "hot_value": " 28250",
      "url": "",
      "description": ""
    },
    {
      "rank": 16,
      "title": "爱泼斯坦别墅内老虎标本栩栩如生",
      "hot_value": " 27923",
      "url": "",
      "description": ""
    },
    {
      "rank": 17,
      "title": "印度大一男生求婚遭拒将女生枪杀",
      "hot_value": " 27420",
      "url": "",
      "description": ""
    },
    {
      "rank": 18,
      "title": "陈星旭 情商",
      "hot_value": " 27327",
      "url": "",
      "description": ""
    },
    {
      "rank": 19,
      "title": "王曼昱决胜局擦边球尊重裁判",
      "hot_value": " 26934",
      "url": "",
      "description": ""
    },
    {
      "rank": 20,
      "title": "郑则仕因不想终生注射药物开始跑步",
      "hot_value": " 26538",
      "url": "",
      "description": ""
    },
    {
      "rank": 21,
      "title": "雷军确认第一代SU7停产",
      "hot_value": " 24530",
      "url": "",
      "description": ""
    },
    {
      "rank": 22,
      "title": "王濛快哭了",
      "hot_value": " 24522",
      "url": "",
      "description": "热"
    },
    {
      "rank": 23,
      "title": "日本彻底失控",
      "hot_value": " 24466",
      "url": "",
      "description": ""
    },
    {
      "rank": 24,
      "title": "孙龙失误",
      "hot_value": " 24420",
      "url": "",
      "description": "热"
    },
    {
      "rank": 25,
      "title": "林孝埈捂脸长时间低头",
      "hot_value": " 24375",
      "url": "",
      "description": ""
    },
    {
      "rank": 26,
      "title": "这3件事是生命力的表现",
      "hot_value": " 24282",
      "url": "",
      "description": ""
    },
    {
      "rank": 27,
      "title": "千问说30亿免单卡快领完了",
      "hot_value": " 24272",
      "url": "",
      "description": ""
    },
    {
      "rank": 28,
      "title": "于正回应明星扎堆前往大孤山",
      "hot_value": " 23478",
      "url": "",
      "description": ""
    },
    {
      "rank": 29,
      "title": "小年",
      "hot_value": " 22906",
      "url": "",
      "description": ""
    },
    {
      "rank": 30,
      "title": "特朗普表面祝贺高市私下大发雷霆",
      "hot_value": " 21810",
      "url": "",
      "description": ""
    },
    {
      "rank": 31,
      "title": "惊蛰无声",
      "hot_value": "电影 21801",
      "url": "",
      "description": ""
    },
    {
      "rank": 32,
      "title": "井柏然刘雯机场十指紧扣",
      "hot_value": " 21768",
      "url": "",
      "description": ""
    },
    {
      "rank": 33,
      "title": "洪世贤掉到榜二了",
      "hot_value": "剧集 20929",
      "url": "",
      "description": ""
    },
    {
      "rank": 34,
      "title": "金博洋男单晋级自由滑",
      "hot_value": " 20713",
      "url": "",
      "description": ""
    },
    {
      "rank": 35,
      "title": "成何体统",
      "hot_value": "剧集 19864",
      "url": "",
      "description": ""
    },
    {
      "rank": 36,
      "title": "镖人",
      "hot_value": "电影 19356",
      "url": "",
      "description": ""
    },
    {
      "rank": 37,
      "title": "韩国又一非法拍摄网站曝光",
      "hot_value": " 19103",
      "url": "",
      "description": ""
    },
    {
      "rank": 38,
      "title": "张杰给100多名员工发超万元红包",
      "hot_value": " 18923",
      "url": "",
      "description": ""
    },
    {
      "rank": 39,
      "title": "春晚",
      "hot_value": "晚会 18721",
      "url": "",
      "description": ""
    },
    {
      "rank": 40,
      "title": "12306回应高铁座椅钻出活蜥蜴",
      "hot_value": " 18490",
      "url": "",
      "description": ""
    },
    {
      "rank": 41,
      "title": "生命树",
      "hot_value": "剧集 16652",
      "url": "",
      "description": ""
    },
    {
      "rank": 42,
      "title": "AI制图骗局",
      "hot_value": " 16220",
      "url": "",
      "description": "热"
    },
    {
      "rank": 43,
      "title": "生命树最讽刺的一幕",
      "hot_value": "剧集 15762",
      "url": "",
      "description": ""
    },
    {
      "rank": 44,
      "title": "堂姐介绍已婚男致女子遇害事后失联",
      "hot_value": " 15634",
      "url": "",
      "description": ""
    },
    {
      "rank": 45,
      "title": "杨洋换风格了",
      "hot_value": " 15623",
      "url": "",
      "description": ""
    },
    {
      "rank": 46,
      "title": "中国短道混接无缘奖牌",
      "hot_value": " 15371",
      "url": "",
      "description": ""
    },
    {
      "rank": 47,
      "title": "易烊千玺晒严迪剧照",
      "hot_value": "电影 15370",
      "url": "",
      "description": ""
    },
    {
      "rank": 48,
      "title": "金博洋短节目clean",
      "hot_value": " 15370",
      "url": "",
      "description": ""
    },
    {
      "rank": 49,
      "title": "短道速滑混团接力",
      "hot_value": " 15369",
      "url": "",
      "description": ""
    },
    {
      "rank": 50,
      "title": "白鹿心疼壁上花案里的女孩",
      "hot_value": "剧集 15369",
      "url": "",
      "description": ""
    },
    {
      "rank": 51,
      "title": "曲春雨退役",
      "hot_value": " 15369",
      "url": "",
      "description": ""
    }
  ],
  "total_count": 51,
  "timestamp": "20260210_223003"
}